[
  {
    "bet_type":"1ST INN ML",
    "game_date":"2026-05-17",
    "home_team":"NYM",
    "away_team":"NYY",
    "home_sp_name":"Freddy Peralta",
    "away_sp_name":"Elmer Rodr\u00edguez",
    "pick":"NYM",
    "odds":-110,
    "model_prob":0.6307,
    "edge":0.1069,
    "edge_pct":"10.7%",
    "confidence":"HIGH",
    "recommended":true,
    "notes":"Strong value",
    "line":null
  },
  {
    "bet_type":"1ST INN ML",
    "game_date":"2026-05-17",
    "home_team":"TB",
    "away_team":"MIA",
    "home_sp_name":"Drew Rasmussen",
    "away_sp_name":"Eury P\u00e9rez",
    "pick":"TB",
    "odds":-110,
    "model_prob":0.6084,
    "edge":0.0846,
    "edge_pct":"8.5%",
    "confidence":"HIGH",
    "recommended":true,
    "notes":"Standard play",
    "line":null
  },
  {
    "bet_type":"1ST INN ML",
    "game_date":"2026-05-17",
    "home_team":"PIT",
    "away_team":"PHI",
    "home_sp_name":"Paul Skenes",
    "away_sp_name":"Zack Wheeler",
    "pick":"PHI",
    "odds":-110,
    "model_prob":0.6013,
    "edge":0.0775,
    "edge_pct":"7.7%",
    "confidence":"HIGH",
    "recommended":false,
    "notes":"Elite pitching matchup",
    "line":null
  },
  {
    "bet_type":"1ST INN ML",
    "game_date":"2026-05-17",
    "home_team":"OAK",
    "away_team":"SF",
    "home_sp_name":"Jeffrey Springs",
    "away_sp_name":"Adrian Houser",
    "pick":"OAK",
    "odds":-110,
    "model_prob":0.6006,
    "edge":0.0768,
    "edge_pct":"7.7%",
    "confidence":"HIGH",
    "recommended":false,
    "notes":"Standard play",
    "line":null
  },
  {
    "bet_type":"1ST INN ML",
    "game_date":"2026-05-17",
    "home_team":"CWS",
    "away_team":"CHC",
    "home_sp_name":"Erick Fedde",
    "away_sp_name":"Colin Rea",
    "pick":"CWS",
    "odds":-110,
    "model_prob":0.5899,
    "edge":0.0661,
    "edge_pct":"6.6%",
    "confidence":"HIGH",
    "recommended":false,
    "notes":"Standard play",
    "line":null
  },
  {
    "bet_type":"1ST INN ML",
    "game_date":"2026-05-17",
    "home_team":"ATL",
    "away_team":"BOS",
    "home_sp_name":"Grant Holmes",
    "away_sp_name":"Brayan Bello",
    "pick":"ATL",
    "odds":-110,
    "model_prob":0.5759,
    "edge":0.0521,
    "edge_pct":"5.2%",
    "confidence":"MEDIUM",
    "recommended":false,
    "notes":"Standard play",
    "line":null
  },
  {
    "bet_type":"1ST INN ML",
    "game_date":"2026-05-17",
    "home_team":"CLE",
    "away_team":"CIN",
    "home_sp_name":"Gavin Williams",
    "away_sp_name":"Brady Singer",
    "pick":"CLE",
    "odds":-110,
    "model_prob":0.55,
    "edge":0.0261,
    "edge_pct":"2.6%",
    "confidence":"NO PLAY",
    "recommended":false,
    "notes":"Standard play",
    "line":null
  },
  {
    "bet_type":"1ST INN ML",
    "game_date":"2026-05-17",
    "home_team":"HOU",
    "away_team":"TEX",
    "home_sp_name":"Peter Lambert",
    "away_sp_name":"Nathan Eovaldi",
    "pick":"TEX",
    "odds":-110,
    "model_prob":0.541,
    "edge":0.0172,
    "edge_pct":"1.7%",
    "confidence":"NO PLAY",
    "recommended":false,
    "notes":"Elite pitching matchup",
    "line":null
  },
  {
    "bet_type":"1ST INN ML",
    "game_date":"2026-05-17",
    "home_team":"COL",
    "away_team":"ARI",
    "home_sp_name":"Michael Lorenzen",
    "away_sp_name":"Michael Soroka",
    "pick":"COL",
    "odds":-110,
    "model_prob":0.5395,
    "edge":0.0157,
    "edge_pct":"1.6%",
    "confidence":"NO PLAY",
    "recommended":false,
    "notes":"Standard play",
    "line":null
  },
  {
    "bet_type":"1ST INN ML",
    "game_date":"2026-05-17",
    "home_team":"MIN",
    "away_team":"MIL",
    "home_sp_name":"Bailey Ober",
    "away_sp_name":"Robert Gasser",
    "pick":"MIN",
    "odds":-110,
    "model_prob":0.5365,
    "edge":0.0127,
    "edge_pct":"1.3%",
    "confidence":"NO PLAY",
    "recommended":false,
    "notes":"Elite pitching matchup",
    "line":null
  },
  {
    "bet_type":"1ST INN ML",
    "game_date":"2026-05-17",
    "home_team":"LAA",
    "away_team":"LAD",
    "home_sp_name":"Grayson Rodriguez",
    "away_sp_name":"Roki Sasaki",
    "pick":"LAA",
    "odds":-110,
    "model_prob":0.5338,
    "edge":0.01,
    "edge_pct":"1.0%",
    "confidence":"NO PLAY",
    "recommended":false,
    "notes":"Standard play",
    "line":null
  },
  {
    "bet_type":"1ST INN ML",
    "game_date":"2026-05-17",
    "home_team":"DET",
    "away_team":"TOR",
    "home_sp_name":"Jack Flaherty",
    "away_sp_name":"Kevin Gausman",
    "pick":"TOR",
    "odds":-110,
    "model_prob":0.5272,
    "edge":0.0034,
    "edge_pct":"0.3%",
    "confidence":"NO PLAY",
    "recommended":false,
    "notes":"Standard play",
    "line":null
  },
  {
    "bet_type":"1ST INN ML",
    "game_date":"2026-05-17",
    "home_team":"SEA",
    "away_team":"SD",
    "home_sp_name":"George Kirby",
    "away_sp_name":"Lucas Giolito",
    "pick":"SEA",
    "odds":-110,
    "model_prob":0.5263,
    "edge":0.0025,
    "edge_pct":"0.2%",
    "confidence":"NO PLAY",
    "recommended":false,
    "notes":"Elite pitching matchup",
    "line":null
  },
  {
    "bet_type":"1ST INN ML",
    "game_date":"2026-05-17",
    "home_team":"STL",
    "away_team":"KC",
    "home_sp_name":"Andre Pallante",
    "away_sp_name":"Stephen Kolek",
    "pick":"STL",
    "odds":-110,
    "model_prob":0.5035,
    "edge":-0.0203,
    "edge_pct":"-2.0%",
    "confidence":"NO PLAY",
    "recommended":false,
    "notes":"Standard play",
    "line":null
  },
  {
    "bet_type":"1ST INN ML",
    "game_date":"2026-05-17",
    "home_team":"WSH",
    "away_team":"BAL",
    "home_sp_name":"Richard Lovelady",
    "away_sp_name":"Brandon Young",
    "pick":"BAL",
    "odds":-110,
    "model_prob":0.5001,
    "edge":-0.0237,
    "edge_pct":"-2.4%",
    "confidence":"NO PLAY",
    "recommended":false,
    "notes":"Elite pitching matchup",
    "line":null
  },
  {
    "bet_type":"1ST INN TOTAL",
    "game_date":"2026-05-17",
    "home_team":"PIT",
    "away_team":"PHI",
    "home_sp_name":"Paul Skenes",
    "away_sp_name":"Zack Wheeler",
    "pick":"OVER 0.5",
    "odds":-110,
    "model_prob":0.5849,
    "edge":0.0611,
    "edge_pct":"6.1%",
    "confidence":"NO PLAY",
    "recommended":false,
    "notes":"Standard play",
    "line":"0.5"
  },
  {
    "bet_type":"1ST INN TOTAL",
    "game_date":"2026-05-17",
    "home_team":"MIN",
    "away_team":"MIL",
    "home_sp_name":"Bailey Ober",
    "away_sp_name":"Robert Gasser",
    "pick":"UNDER 0.5",
    "odds":-110,
    "model_prob":0.5709,
    "edge":0.0471,
    "edge_pct":"4.7%",
    "confidence":"NO PLAY",
    "recommended":false,
    "notes":"Elite SPs keep 1st clean",
    "line":"0.5"
  },
  {
    "bet_type":"1ST INN TOTAL",
    "game_date":"2026-05-17",
    "home_team":"ATL",
    "away_team":"BOS",
    "home_sp_name":"Grant Holmes",
    "away_sp_name":"Brayan Bello",
    "pick":"OVER 0.5",
    "odds":-110,
    "model_prob":0.5693,
    "edge":0.0454,
    "edge_pct":"4.5%",
    "confidence":"NO PLAY",
    "recommended":false,
    "notes":"Standard play",
    "line":"0.5"
  },
  {
    "bet_type":"1ST INN TOTAL",
    "game_date":"2026-05-17",
    "home_team":"DET",
    "away_team":"TOR",
    "home_sp_name":"Jack Flaherty",
    "away_sp_name":"Kevin Gausman",
    "pick":"UNDER 0.5",
    "odds":-110,
    "model_prob":0.5673,
    "edge":0.0435,
    "edge_pct":"4.3%",
    "confidence":"NO PLAY",
    "recommended":false,
    "notes":"Standard play",
    "line":"0.5"
  },
  {
    "bet_type":"1ST INN TOTAL",
    "game_date":"2026-05-17",
    "home_team":"COL",
    "away_team":"ARI",
    "home_sp_name":"Michael Lorenzen",
    "away_sp_name":"Michael Soroka",
    "pick":"OVER 0.5",
    "odds":-110,
    "model_prob":0.5376,
    "edge":0.0138,
    "edge_pct":"1.4%",
    "confidence":"NO PLAY",
    "recommended":false,
    "notes":"Hitter-friendly park",
    "line":"0.5"
  },
  {
    "bet_type":"1ST INN TOTAL",
    "game_date":"2026-05-17",
    "home_team":"SEA",
    "away_team":"SD",
    "home_sp_name":"George Kirby",
    "away_sp_name":"Lucas Giolito",
    "pick":"OVER 0.5",
    "odds":-110,
    "model_prob":0.5364,
    "edge":0.0126,
    "edge_pct":"1.3%",
    "confidence":"NO PLAY",
    "recommended":false,
    "notes":"Standard play",
    "line":"0.5"
  },
  {
    "bet_type":"1ST INN TOTAL",
    "game_date":"2026-05-17",
    "home_team":"HOU",
    "away_team":"TEX",
    "home_sp_name":"Peter Lambert",
    "away_sp_name":"Nathan Eovaldi",
    "pick":"OVER 0.5",
    "odds":-110,
    "model_prob":0.5359,
    "edge":0.0121,
    "edge_pct":"1.2%",
    "confidence":"NO PLAY",
    "recommended":false,
    "notes":"Standard play",
    "line":"0.5"
  },
  {
    "bet_type":"1ST INN TOTAL",
    "game_date":"2026-05-17",
    "home_team":"OAK",
    "away_team":"SF",
    "home_sp_name":"Jeffrey Springs",
    "away_sp_name":"Adrian Houser",
    "pick":"UNDER 0.5",
    "odds":-110,
    "model_prob":0.5268,
    "edge":0.0029,
    "edge_pct":"0.3%",
    "confidence":"NO PLAY",
    "recommended":false,
    "notes":"Standard play",
    "line":"0.5"
  },
  {
    "bet_type":"1ST INN TOTAL",
    "game_date":"2026-05-17",
    "home_team":"WSH",
    "away_team":"BAL",
    "home_sp_name":"Richard Lovelady",
    "away_sp_name":"Brandon Young",
    "pick":"OVER 0.5",
    "odds":-110,
    "model_prob":0.5202,
    "edge":-0.0036,
    "edge_pct":"-0.4%",
    "confidence":"NO PLAY",
    "recommended":false,
    "notes":"Standard play",
    "line":"0.5"
  },
  {
    "bet_type":"1ST INN TOTAL",
    "game_date":"2026-05-17",
    "home_team":"STL",
    "away_team":"KC",
    "home_sp_name":"Andre Pallante",
    "away_sp_name":"Stephen Kolek",
    "pick":"UNDER 0.5",
    "odds":-110,
    "model_prob":0.5203,
    "edge":-0.0036,
    "edge_pct":"-0.4%",
    "confidence":"NO PLAY",
    "recommended":false,
    "notes":"Standard play",
    "line":"0.5"
  },
  {
    "bet_type":"1ST INN TOTAL",
    "game_date":"2026-05-17",
    "home_team":"NYM",
    "away_team":"NYY",
    "home_sp_name":"Freddy Peralta",
    "away_sp_name":"Elmer Rodr\u00edguez",
    "pick":"OVER 0.5",
    "odds":-110,
    "model_prob":0.5181,
    "edge":-0.0057,
    "edge_pct":"-0.6%",
    "confidence":"NO PLAY",
    "recommended":false,
    "notes":"Standard play",
    "line":"0.5"
  },
  {
    "bet_type":"1ST INN TOTAL",
    "game_date":"2026-05-17",
    "home_team":"LAA",
    "away_team":"LAD",
    "home_sp_name":"Grayson Rodriguez",
    "away_sp_name":"Roki Sasaki",
    "pick":"OVER 0.5",
    "odds":-110,
    "model_prob":0.5163,
    "edge":-0.0075,
    "edge_pct":"-0.7%",
    "confidence":"NO PLAY",
    "recommended":false,
    "notes":"Standard play",
    "line":"0.5"
  },
  {
    "bet_type":"1ST INN TOTAL",
    "game_date":"2026-05-17",
    "home_team":"TB",
    "away_team":"MIA",
    "home_sp_name":"Drew Rasmussen",
    "away_sp_name":"Eury P\u00e9rez",
    "pick":"OVER 0.5",
    "odds":-110,
    "model_prob":0.5153,
    "edge":-0.0086,
    "edge_pct":"-0.9%",
    "confidence":"NO PLAY",
    "recommended":false,
    "notes":"Standard play",
    "line":"0.5"
  },
  {
    "bet_type":"1ST INN TOTAL",
    "game_date":"2026-05-17",
    "home_team":"CWS",
    "away_team":"CHC",
    "home_sp_name":"Erick Fedde",
    "away_sp_name":"Colin Rea",
    "pick":"OVER 0.5",
    "odds":-110,
    "model_prob":0.5037,
    "edge":-0.0201,
    "edge_pct":"-2.0%",
    "confidence":"NO PLAY",
    "recommended":false,
    "notes":"Standard play",
    "line":"0.5"
  },
  {
    "bet_type":"1ST INN TOTAL",
    "game_date":"2026-05-17",
    "home_team":"CLE",
    "away_team":"CIN",
    "home_sp_name":"Gavin Williams",
    "away_sp_name":"Brady Singer",
    "pick":"OVER 0.5",
    "odds":-110,
    "model_prob":0.5033,
    "edge":-0.0205,
    "edge_pct":"-2.0%",
    "confidence":"NO PLAY",
    "recommended":false,
    "notes":"Standard play",
    "line":"0.5"
  }
]